whitehole/__init__.py
whitehole/decryptor.py
whitehole/notebooks/__init__.py
whitehole/tests/__init__.py
whitehole/tests/test_decryptor.py
whitehole-0.0.3.dist-info/LICENSE
whitehole-0.0.3.dist-info/METADATA
whitehole-0.0.3.dist-info/WHEEL
whitehole-0.0.3.dist-info/top_level.txt
whitehole-0.0.3.dist-info/RECORD
