Metadata-Version: 2.1
Name: whitehole
Version: 0.0.3
Summary: Package for read and backtest data of financial assets in the most storage-efficient way, taking care of performance and store using zarr format files
Home-page: https://github.com/quantmoon/whitehole
Author: QuantMoon Technologies
Author-email: contacto@quantmoon.com
License: UNKNOWN
Platform: UNKNOWN
Classifier: Programming Language :: Python :: 3
Classifier: License :: OSI Approved :: MIT License
Classifier: Operating System :: Microsoft :: Windows
Requires-Python: >=3.5
Requires-Dist: pandas (>=0.22.0)
Requires-Dist: numpy (>=1.18.2)
Requires-Dist: zarr
Requires-Dist: xarray (>=0.13.0)
Requires-Dist: pandas-market-calendars (>=1.4.2)
